ptsqld/__init__.py
ptsqld/__init__.py~
ptsqld/__main__.py~
ptsqld/structured_engine.py
ptsqld/structured_engine.py~
ptsqld/structured_vault.py
ptsqld/structuredvault.py~
ptsqld-0.1.7.dist-info/METADATA
ptsqld-0.1.7.dist-info/WHEEL
ptsqld-0.1.7.dist-info/RECORD
