Metadata-Version: 2.1
Name: ptsqld
Version: 0.1.7
Summary: An SQL Database which shall avoid any further PTSD associated to other SQL Database setup (understand flexible, simple)
Author: Charles Bajeux
Author-email: charles.bajeux@gmail.com
Requires-Python: >=3.11,<4.0
Classifier: Programming Language :: Python :: 3
Classifier: Programming Language :: Python :: 3.11
Classifier: Programming Language :: Python :: 3.12
Requires-Dist: echovault (>=0.2.3,<0.3.0)
Requires-Dist: sqletic (>=0.1.4,<0.2.0)
